yapper/__init__.py
yapper/constants.py
yapper/core.py
yapper/enhancer.py
yapper/enums.py
yapper/meta.py
yapper/speaker.py
yapper/utils.py
yapper_tts-0.7.2.dist-info/licenses/LICENSE
yapper_tts-0.7.2.dist-info/METADATA
yapper_tts-0.7.2.dist-info/WHEEL
yapper_tts-0.7.2.dist-info/top_level.txt
yapper_tts-0.7.2.dist-info/RECORD
