Metadata-Version: 2.4
Name: yapper-tts
Version: 0.7.2
Summary: AI powered text-ehancer and offline text-to-speech
Home-page: https://github.com/n1teshy/yapper-tts
Author: Nitesh Yadav
Author-email: nitesh.txt@gmail.com
License: MIT
Keywords: text-to-speech,offline text-to-speech,tts,speech synthesis
Platform: Posix; Windows
Classifier: Intended Audience :: Developers
Classifier: Programming Language :: Python
Classifier: Programming Language :: Python :: 3
Classifier: Programming Language :: Python :: 3.9
Classifier: Programming Language :: Python :: 3.10
Classifier: Programming Language :: Python :: 3.11
Classifier: Programming Language :: Python :: 3.12
Classifier: License :: OSI Approved :: MIT License
Classifier: Operating System :: OS Independent
Requires-Python: >=3.9
License-File: LICENSE
Requires-Dist: pyttsx3
Requires-Dist: pygame
Dynamic: author
Dynamic: author-email
Dynamic: classifier
Dynamic: description
Dynamic: description-content-type
Dynamic: home-page
Dynamic: keywords
Dynamic: license
Dynamic: license-file
Dynamic: platform
Dynamic: requires-dist
Dynamic: requires-python
Dynamic: summary
